{
  "id": "pillars",
  "title": "Five Pillars",
  "folder": "pillars",
  "engine": "spotlight",
  "renderer": "reference-visual",
  "controls": "floating",
  "enabled": true,
  "showOnLanding": true,
  "backgroundImage": "pillars/pillars.jpeg",
  "tileImage": "pillars/pillars_icon.jpeg",
  "effect": {
    "type": "referencePillars",
    "style": "pillarFocus-soft-sparkle-idle",
    "dimOthers": true,
    "border": "colorful",
    "sparkles": true,
    "sparkleRate": 1000,
    "maxScale": 1.035
  },
  "coordinates": {
    "shahadah": {
      "left": 11.15,
      "top": 60.150000000000006,
      "width": 7.7,
      "height": 11.1
    },
    "salah": {
      "left": 29.75,
      "top": 60.150000000000006,
      "width": 7.7,
      "height": 11.1
    },
    "zakat": {
      "left": 47.55,
      "top": 60.150000000000006,
      "width": 7.7,
      "height": 11.1
    },
    "sawm": {
      "left": 63.85,
      "top": 60.150000000000006,
      "width": 7.7,
      "height": 11.1
    },
    "hajj": {
      "left": 82.25,
      "top": 60.150000000000006,
      "width": 7.7,
      "height": 11.1
    }
  },
  "coordinateTiming": {
    "source": "audio-starts",
    "unit": "seconds",
    "starts": {
      "shahadah": 0.0,
      "salah": 13.5,
      "zakat": 20.28,
      "sawm": 25.57,
      "hajj": 34.01
    },
    "ranges": {
      "shahadah": [
        0.0,
        12.8
      ],
      "salah": [
        13.5,
        20.2
      ],
      "zakat": [
        20.28,
        25.3
      ],
      "sawm": [
        25.57,
        32.96
      ],
      "hajj": [
        34.01,
        40.63
      ]
    }
  },
  "landingTileImage": true,
  "aspectRatio": "3/2",
  "primaryAudio": "pillars/pillars.mp3",
  "audios": [
    "pillars/pillars.mp3"
  ],
  "theme": "pillars"
}
